practicalSPARQL.py
practicalSPARQL-0.0.6.dist-info/LICENSE.txt
practicalSPARQL-0.0.6.dist-info/METADATA
practicalSPARQL-0.0.6.dist-info/WHEEL
practicalSPARQL-0.0.6.dist-info/top_level.txt
practicalSPARQL-0.0.6.dist-info/RECORD
