Metadata-Version: 2.1
Name: practicalSPARQL
Version: 0.0.6
Summary: Small wrapper to simplify the interaction with SPARQL endpoints. Built on top of sparqlwrapper and RDFlib
Home-page: https://github.com/hassanhajj910/practicalsparql
Author: hassanhajj910@gmail.com
Classifier: Programming Language :: Python :: 3
Classifier: Programming Language :: Python :: 3.8
Classifier: License :: OSI Approved :: MIT License
Classifier: Operating System :: OS Independent
License-File: LICENSE.txt
Requires-Dist: SPARQLWrapper
Requires-Dist: rdflib
Requires-Dist: numpy
